{"type":"FeatureCollection","features":[{"type":"Feature","geometry":{"type":"Point","coordinates":[72.9861437,19.2474796]},"properties":{"name":"Brahmand","position":0,"ref":"2475"}},{"type":"Feature","geometry":{"type":"Point","coordinates":[72.984676,19.2464836]},"properties":{"name":"Brahmand Phase 6","position":1,"ref":"2476"}},{"type":"Feature","geometry":{"type":"Point","coordinates":[72.9835585,19.2449052]},"properties":{"name":"Brahmand Phase 5","position":2,"ref":"2477"}},{"type":"Feature","geometry":{"type":"Point","coordinates":[72.9829271,19.2433852]},"properties":{"name":"Swastik Park","position":3,"ref":"2478"}},{"type":"Feature","geometry":{"type":"Point","coordinates":[72.9815827,19.241132]},"properties":{"name":"Brahmand Phase 4","position":4,"ref":"2479"}},{"type":"Feature","geometry":{"type":"Point","coordinates":[72.9806686,19.2394597]},"properties":{"name":"Azad Nagar","position":5,"ref":"2480"}},{"type":"Feature","geometry":{"type":"Point","coordinates":[72.9774694,19.2403545]},"properties":{"name":"St. Xavier School","position":6,"ref":"2481"}},{"type":"Feature","geometry":{"type":"Point","coordinates":[72.9758927,19.2410253]},"properties":{"name":"Azad Nagar Naka","position":7,"ref":"2482"}},{"type":"Feature","geometry":{"type":"Point","coordinates":[72.9758218,19.2393251]},"properties":{"name":"Mulla Bagh","position":8,"ref":"2483"}},{"type":"Feature","geometry":{"type":"Point","coordinates":[72.976308,19.2352853]},"properties":{"name":"Manpada","position":9,"ref":"2484"}},{"type":"Feature","geometry":{"type":"Point","coordinates":[72.9768618,19.2301954]},"properties":{"name":"Lockim Company / R Mall","position":10,"ref":"2485"}},{"type":"Feature","geometry":{"type":"Point","coordinates":[72.97761,19.22391]},"properties":{"name":"Tattvagyan Vidyapeeth","position":11,"ref":"2486"}},{"type":"Feature","geometry":{"type":"Point","coordinates":[72.9779764,19.2207986]},"properties":{"name":"Kapurbawdi","position":12,"ref":"2487"}},{"type":"Feature","geometry":{"type":"Point","coordinates":[72.97797,19.21555]},"properties":{"name":"Ashapura Mandir","position":13,"ref":"2488"}},{"type":"Feature","geometry":{"type":"Point","coordinates":[72.9779923,19.2143155]},"properties":{"name":"Majiwada Naka","position":14,"ref":"2489"}},{"type":"Feature","geometry":{"type":"Point","coordinates":[72.97749,19.21058]},"properties":{"name":"Muktai Nagar","position":15,"ref":"2490"}},{"type":"Feature","geometry":{"type":"Point","coordinates":[72.97713,19.20886]},"properties":{"name":"Gokul Nagar","position":16,"ref":"2491"}},{"type":"Feature","geometry":{"type":"Point","coordinates":[72.97746,19.20747]},"properties":{"name":"Ambika Yog Kutir","position":17,"ref":"2492"}},{"type":"Feature","geometry":{"type":"Point","coordinates":[72.9777117,19.2063413]},"properties":{"name":"Abhiruchi","position":18,"ref":"2493"}},{"type":"Feature","geometry":{"type":"Point","coordinates":[72.97884,19.20118]},"properties":{"name":"Police Line","position":19,"ref":"2494"}},{"type":"Feature","geometry":{"type":"Point","coordinates":[72.9799736,19.1979212]},"properties":{"name":"Central Maidan","position":20,"ref":"2495"}},{"type":"Feature","geometry":{"type":"Point","coordinates":[72.9785372,19.1970513]},"properties":{"name":"Court Naka","position":21,"ref":"2496"}},{"type":"Feature","geometry":{"type":"Point","coordinates":[72.97791,19.19457]},"properties":{"name":"Jambhali Naka","position":22,"ref":"799"}},{"type":"Feature","geometry":{"type":"Point","coordinates":[72.9769207,19.1905235]},"properties":{"name":"Prabhat Cinema","position":23,"ref":"2497"}},{"type":"Feature","geometry":{"type":"Point","coordinates":[72.9772115,19.1871306]},"properties":{"name":"Thane Station West SATIS","position":24,"ref":"2498"}}]}