{"type":"FeatureCollection","features":[{"type":"Feature","geometry":{"type":"Point","coordinates":[72.9658822,19.2370451]},"properties":{"name":"Tikujiniwadi","position":0,"ref":"902"}},{"type":"Feature","geometry":{"type":"Point","coordinates":[72.9660459,19.2347026]},"properties":{"name":"Hill Garden","position":1,"ref":"903"}},{"type":"Feature","geometry":{"type":"Point","coordinates":[72.9657345,19.233616]},"properties":{"name":"Koknipada","position":2,"ref":"904"}},{"type":"Feature","geometry":{"type":"Point","coordinates":[72.9677871,19.2330334]},"properties":{"name":"Garden Est.","position":3,"ref":"905"}},{"type":"Feature","geometry":{"type":"Point","coordinates":[72.9697749,19.2325898]},"properties":{"name":"Khevra Cercal","position":4,"ref":"906"}},{"type":"Feature","geometry":{"type":"Point","coordinates":[72.9702312,19.2366206]},"properties":{"name":"Dharmveer Ngar / Happy Valley","position":5,"ref":"907"}},{"type":"Feature","geometry":{"type":"Point","coordinates":[72.9727656,19.2364135]},"properties":{"name":"Sahayog Soc","position":6,"ref":"908"}},{"type":"Feature","geometry":{"type":"Point","coordinates":[72.9763056,19.2352849]},"properties":{"name":"Manpada","position":7,"ref":"909"}},{"type":"Feature","geometry":{"type":"Point","coordinates":[72.9768782,19.230196]},"properties":{"name":"Lockim / R Mall","position":8,"ref":"910"}},{"type":"Feature","geometry":{"type":"Point","coordinates":[72.9776154,19.2239249]},"properties":{"name":"Vidyapith","position":9,"ref":"911"}},{"type":"Feature","geometry":{"type":"Point","coordinates":[72.9779878,19.2208021]},"properties":{"name":"Kapurbavdi","position":10,"ref":"912"}},{"type":"Feature","geometry":{"type":"Point","coordinates":[72.9781557,19.2157381]},"properties":{"name":"Aashapura Mndir","position":11,"ref":"913"}},{"type":"Feature","geometry":{"type":"Point","coordinates":[72.9779939,19.2143162]},"properties":{"name":"Majiwada Naka","position":12,"ref":"914"}},{"type":"Feature","geometry":{"type":"Point","coordinates":[72.9772714,19.2105743]},"properties":{"name":"Muktaingar","position":13,"ref":"915"}},{"type":"Feature","geometry":{"type":"Point","coordinates":[72.977135,19.2088869]},"properties":{"name":"Gokulngar","position":14,"ref":"916"}},{"type":"Feature","geometry":{"type":"Point","coordinates":[72.9774895,19.2071034]},"properties":{"name":"Ambika Yogkutir","position":15,"ref":"917"}},{"type":"Feature","geometry":{"type":"Point","coordinates":[72.9773097,19.2041224]},"properties":{"name":"Kolbad","position":16,"ref":"918"}},{"type":"Feature","geometry":{"type":"Point","coordinates":[72.9763367,19.2026165]},"properties":{"name":"Bramhla Talav/ Mnorpada","position":17,"ref":"919"}},{"type":"Feature","geometry":{"type":"Point","coordinates":[72.9732858,19.2006011]},"properties":{"name":"St Work Shop","position":18,"ref":"920"}},{"type":"Feature","geometry":{"type":"Point","coordinates":[72.9718472,19.1984375]},"properties":{"name":"Mkhamali Talav","position":19,"ref":"921"}},{"type":"Feature","geometry":{"type":"Point","coordinates":[72.9705386,19.194198]},"properties":{"name":"Vandna Cinema","position":20,"ref":"922"}},{"type":"Feature","geometry":{"type":"Point","coordinates":[72.9679535,19.1912479]},"properties":{"name":"Harinivas","position":21,"ref":"923"}},{"type":"Feature","geometry":{"type":"Point","coordinates":[72.9686439,19.1873668]},"properties":{"name":"Ice Factory","position":22,"ref":"924"}},{"type":"Feature","geometry":{"type":"Point","coordinates":[72.9717434,19.1876851]},"properties":{"name":"A K Joshi","position":23,"ref":"925"}},{"type":"Feature","geometry":{"type":"Point","coordinates":[72.9746802,19.1887765]},"properties":{"name":"Gavdevi Mandir Thane (w)","position":24,"ref":"926"}},{"type":"Feature","geometry":{"type":"Point","coordinates":[72.976106,19.186713]},"properties":{"name":"Thane Station West Satis","position":25,"ref":"927"}}]}